Rungui/__init__.py
Rungui-3.0.1.dist-info/METADATA
Rungui-3.0.1.dist-info/WHEEL
Rungui-3.0.1.dist-info/top_level.txt
Rungui-3.0.1.dist-info/RECORD
