Metadata-Version: 2.1
Name: Rungui
Version: 3.0.1
Summary: Anti Skid package to run a gui
Home-page: https://fuck-lgbtq.com
Author: vesper
Author-email: balls@gmail.com
License: MIT
Keywords: idk
Platform: UNKNOWN
Classifier: Development Status :: 5 - Production/Stable
Classifier: Intended Audience :: Education
Classifier: Operating System :: Microsoft :: Windows :: Windows 10
Classifier: License :: OSI Approved :: MIT License
Classifier: Programming Language :: Python :: 3
